pygascard/__init__.py
pygascard/codes.json
pygascard/comm.py
pygascard/daq.py
pygascard/device.py
pygascard/util.py
pygascard-0.0.11.dist-info/LICENSE
pygascard-0.0.11.dist-info/METADATA
pygascard-0.0.11.dist-info/WHEEL
pygascard-0.0.11.dist-info/RECORD
