Metadata-Version: 2.1
Name: pygascard
Version: 0.0.11
Summary: Python API for acquisition and control of Edinburgh Sensors Gascard
Home-page: https://github.com/ulfsri/pyGascard
License: MIT
Author: ulfsri
Author-email: grayson.bellamy@ul.org
Requires-Python: >=3.12,<4.0
Classifier: Development Status :: 3 - Alpha
Classifier: Intended Audience :: Developers
Classifier: License :: OSI Approved :: MIT License
Classifier: Operating System :: OS Independent
Classifier: Programming Language :: Python :: 3
Classifier: Programming Language :: Python :: 3.12
Classifier: Topic :: Software Development :: Libraries :: Python Modules
Requires-Dist: anyserial (>=0.1.0,<0.2.0)
Requires-Dist: asyncpg (>=0.29.0,<0.30.0)
Requires-Dist: uvloop (>=0.19.0,<0.20.0)
Project-URL: Repository, https://github.com/ulfsri/pyGascard
